pywindow/__init__.py
pywindow/_windows.py
pywindow/appwindow.py
pywindow-0.0.3.dist-info/DESCRIPTION.rst
pywindow-0.0.3.dist-info/METADATA
pywindow-0.0.3.dist-info/RECORD
pywindow-0.0.3.dist-info/WHEEL
pywindow-0.0.3.dist-info/metadata.json
pywindow-0.0.3.dist-info/top_level.txt
