Metadata-Version: 2.0
Name: pywindow
Version: 0.0.3
Summary: My short description for my project.
Home-page: https://github.com/evfredericsen/pywindow
Author: Evan Fredericksen
Author-email: UNKNOWN
License: MIT
Platform: UNKNOWN
Classifier: License :: OSI Approved :: MIT License
Classifier: Programming Language :: Python
Classifier: Programming Language :: Python :: 3
Classifier: Programming Language :: Python :: 3.6
Classifier: Programming Language :: Python :: Implementation :: CPython
